[
  {
    "url": "https://api.github.com/repos/Expensify/App/issues/71745",
    "repository_url": "https://api.github.com/repos/Expensify/App",
    "labels_url": "https://api.github.com/repos/Expensify/App/issues/71745/labels{/name}",
    "comments_url": "https://api.github.com/repos/Expensify/App/issues/71745/comments",
    "events_url": "https://api.github.com/repos/Expensify/App/issues/71745/events",
    "html_url": "https://github.com/Expensify/App/issues/71745",
    "id": 3476606530,
    "node_id": "I_kwDOEQqHYc7POM5C",
    "number": 71745,
    "title": "[$250] Workspace - Forced to upgrade workspace, Workflows is still disabled after upgrade",
    "user": {
      "login": "mitarachim",
      "id": 181838622,
      "node_id": "U_kgDOCtajHg",
      "avatar_url": "https://avatars.githubusercontent.com/u/181838622?v=4",
      "gravatar_id": "",
      "url": "https://api.github.com/users/mitarachim",
      "html_url": "https://github.com/mitarachim",
      "followers_url": "https://api.github.com/users/mitarachim/followers",
      "following_url": "https://api.github.com/users/mitarachim/following{/other_user}",
      "gists_url": "https://api.github.com/users/mitarachim/gists{/gist_id}",
      "starred_url": "https://api.github.com/users/mitarachim/starred{/owner}{/repo}",
      "subscriptions_url": "https://api.github.com/users/mitarachim/subscriptions",
      "organizations_url": "https://api.github.com/users/mitarachim/orgs",
      "repos_url": "https://api.github.com/users/mitarachim/repos",
      "events_url": "https://api.github.com/users/mitarachim/events{/privacy}",
      "received_events_url": "https://api.github.com/users/mitarachim/received_events",
      "type": "User",
      "user_view_type": "public",
      "site_admin": false
    },
    "labels": [
      {
        "id": 2810597462,
        "node_id": "MDU6TGFiZWwyODEwNTk3NDYy",
        "url": "https://api.github.com/repos/Expensify/App/labels/DeployBlockerCash",
        "name": "DeployBlockerCash",
        "color": "000000",
        "default": false,
        "description": "This issue or pull request should block deployment"
      },
      {
        "id": 2873246102,
        "node_id": "MDU6TGFiZWwyODczMjQ2MTAy",
        "url": "https://api.github.com/repos/Expensify/App/labels/External",
        "name": "External",
        "color": "a7b8ef",
        "default": false,
        "description": "Added to denote the issue can be worked on by a contributor"
      },
      {
        "id": 2873635554,
        "node_id": "MDU6TGFiZWwyODczNjM1NTU0",
        "url": "https://api.github.com/repos/Expensify/App/labels/Engineering",
        "name": "Engineering",
        "color": "274073",
        "default": false,
        "description": ""
      },
      {
        "id": 3008326907,
        "node_id": "MDU6TGFiZWwzMDA4MzI2OTA3",
        "url": "https://api.github.com/repos/Expensify/App/labels/Hourly",
        "name": "Hourly",
        "color": "EC0E2D",
        "default": false,
        "description": "KSv2"
      },
      {
        "id": 3136662525,
        "node_id": "MDU6TGFiZWwzMTM2NjYyNTI1",
        "url": "https://api.github.com/repos/Expensify/App/labels/Help%20Wanted",
        "name": "Help Wanted",
        "color": "CFC8F1",
        "default": false,
        "description": "Apply this label when an issue is open to proposals by contributors"
      },
      {
        "id": 4664850679,
        "node_id": "LA_kwDOEQqHYc8AAAABFgv49w",
        "url": "https://api.github.com/repos/Expensify/App/labels/Bug",
        "name": "Bug",
        "color": "93074F",
        "default": false,
        "description": "Something is broken. Auto assigns a BugZero manager."
      },
      {
        "id": 6901200133,
        "node_id": "LA_kwDOEQqHYc8AAAABm1f1BQ",
        "url": "https://api.github.com/repos/Expensify/App/labels/DeployBlocker",
        "name": "DeployBlocker",
        "color": "D93F0B",
        "default": false,
        "description": "Indicates it should block deploying the API"
      }
    ],
    "state": "open",
    "locked": false,
    "assignee": {
      "login": "twisterdotcom",
      "id": 9133401,
      "node_id": "MDQ6VXNlcjkxMzM0MDE=",
      "avatar_url": "https://avatars.githubusercontent.com/u/9133401?v=4",
      "gravatar_id": "",
      "url": "https://api.github.com/users/twisterdotcom",
      "html_url": "https://github.com/twisterdotcom",
      "followers_url": "https://api.github.com/users/twisterdotcom/followers",
      "following_url": "https://api.github.com/users/twisterdotcom/following{/other_user}",
      "gists_url": "https://api.github.com/users/twisterdotcom/gists{/gist_id}",
      "starred_url": "https://api.github.com/users/twisterdotcom/starred{/owner}{/repo}",
      "subscriptions_url": "https://api.github.com/users/twisterdotcom/subscriptions",
      "organizations_url": "https://api.github.com/users/twisterdotcom/orgs",
      "repos_url": "https://api.github.com/users/twisterdotcom/repos",
      "events_url": "https://api.github.com/users/twisterdotcom/events{/privacy}",
      "received_events_url": "https://api.github.com/users/twisterdotcom/received_events",
      "type": "User",
      "user_view_type": "public",
      "site_admin": false
    },
    "assignees": [
      {
        "login": "twisterdotcom",
        "id": 9133401,
        "node_id": "MDQ6VXNlcjkxMzM0MDE=",
        "avatar_url": "https://avatars.githubusercontent.com/u/9133401?v=4",
        "gravatar_id": "",
        "url": "https://api.github.com/users/twisterdotcom",
        "html_url": "https://github.com/twisterdotcom",
        "followers_url": "https://api.github.com/users/twisterdotcom/followers",
        "following_url": "https://api.github.com/users/twisterdotcom/following{/other_user}",
        "gists_url": "https://api.github.com/users/twisterdotcom/gists{/gist_id}",
        "starred_url": "https://api.github.com/users/twisterdotcom/starred{/owner}{/repo}",
        "subscriptions_url": "https://api.github.com/users/twisterdotcom/subscriptions",
        "organizations_url": "https://api.github.com/users/twisterdotcom/orgs",
        "repos_url": "https://api.github.com/users/twisterdotcom/repos",
        "events_url": "https://api.github.com/users/twisterdotcom/events{/privacy}",
        "received_events_url": "https://api.github.com/users/twisterdotcom/received_events",
        "type": "User",
        "user_view_type": "public",
        "site_admin": false
      },
      {
        "login": "Gonals",
        "id": 19366280,
        "node_id": "MDQ6VXNlcjE5MzY2Mjgw",
        "avatar_url": "https://avatars.githubusercontent.com/u/19366280?v=4",
        "gravatar_id": "",
        "url": "https://api.github.com/users/Gonals",
        "html_url": "https://github.com/Gonals",
        "followers_url": "https://api.github.com/users/Gonals/followers",
        "following_url": "https://api.github.com/users/Gonals/following{/other_user}",
        "gists_url": "https://api.github.com/users/Gonals/gists{/gist_id}",
        "starred_url": "https://api.github.com/users/Gonals/starred{/owner}{/repo}",
        "subscriptions_url": "https://api.github.com/users/Gonals/subscriptions",
        "organizations_url": "https://api.github.com/users/Gonals/orgs",
        "repos_url": "https://api.github.com/users/Gonals/repos",
        "events_url": "https://api.github.com/users/Gonals/events{/privacy}",
        "received_events_url": "https://api.github.com/users/Gonals/received_events",
        "type": "User",
        "user_view_type": "public",
        "site_admin": false
      },
      {
        "login": "jayeshmangwani",
        "id": 35371050,
        "node_id": "MDQ6VXNlcjM1MzcxMDUw",
        "avatar_url": "https://avatars.githubusercontent.com/u/35371050?v=4",
        "gravatar_id": "",
        "url": "https://api.github.com/users/jayeshmangwani",
        "html_url": "https://github.com/jayeshmangwani",
        "followers_url": "https://api.github.com/users/jayeshmangwani/followers",
        "following_url": "https://api.github.com/users/jayeshmangwani/following{/other_user}",
        "gists_url": "https://api.github.com/users/jayeshmangwani/gists{/gist_id}",
        "starred_url": "https://api.github.com/users/jayeshmangwani/starred{/owner}{/repo}",
        "subscriptions_url": "https://api.github.com/users/jayeshmangwani/subscriptions",
        "organizations_url": "https://api.github.com/users/jayeshmangwani/orgs",
        "repos_url": "https://api.github.com/users/jayeshmangwani/repos",
        "events_url": "https://api.github.com/users/jayeshmangwani/events{/privacy}",
        "received_events_url": "https://api.github.com/users/jayeshmangwani/received_events",
        "type": "User",
        "user_view_type": "public",
        "site_admin": false
      }
    ],
    "milestone": null,
    "comments": 7,
    "created_at": "2025-10-02T08:32:48Z",
    "updated_at": "2025-10-02T12:31:50Z",
    "closed_at": null,
    "author_association": "NONE",
    "type": null,
    "active_lock_reason": null,
    "sub_issues_summary": {
      "total": 0,
      "completed": 0,
      "percent_completed": 0
    },
    "issue_dependencies_summary": {
      "blocked_by": 0,
      "total_blocked_by": 0,
      "blocking": 0,
      "total_blocking": 0
    },
    "body": "If you haven’t already, check out our [contributing guidelines](https://github.com/Expensify/ReactNativeChat/blob/main/contributingGuides/CONTRIBUTING.md) for onboarding and email contributors@expensify.com to request to join our Slack channel!\n___\n\n**Version Number:** 9.2.22-1\n**Reproducible in staging?:** Yes\n**Reproducible in production?:** N/A - new feature, doesn't exist in prod\n**If this was caught during regression testing, add the test name, ID and link from TestRail:** https://github.com/Expensify/App/pull/70362\n**Email or phone of affected tester (no customers):** jsdnoijsdojsoij@gmail.com\n**Issue reported by:** Applause Internal Team\n**Device used:** Mac 15.5 / Chrome\n**App Component:** Workspace Settings\n\n## Action Performed:\n1. Go to staging.new.expensify.com\n2. Create a new workspace.\n3. Go to workspace settings > More features.\n4. Disable Workflows.\n5. Go to Members and invite a member.\n6. Click More > Download CSV.\n7. Create another workspace and also disable Workflows in workspace settings > More features.\n8. Go to Members.\n9. Click More > Import spreadsheet.\n10. Upload the CSV from Step 6.\n11. Click Import.\n\n## Expected Result:\n- User should not be forced to upgrade when the CSV file does not contain additional approver or additional workflow.\n- After upgrading to enable \"Advanced Approvals\", Workflows should be enabled.\n\n## Actual Result:\n- User is forced to upgrade when the CSV file does not contain additional approver or additional workflow.\n- After upgrading to enable \"Advanced Approvals\", Workflows is still disabled.\n\n## Workaround:\nUnknown\n\n## Platforms:\n- [x] Android: App\n- [x] Android: mWeb Chrome\n- [x] iOS: App\n- [x] iOS: mWeb Safari\n- [x] iOS: mWeb Chrome\n- [ ] Windows: Chrome\n- [x] MacOS: Chrome / Safari\n- [x] MacOS: Desktop\n\n## Screenshots/Videos\n\nhttps://github.com/user-attachments/assets/710ec524-90c6-4b2c-88b0-5aa3d7dd3ea5\n\n[View all open jobs on GitHub](https://github.com/Expensify/App/issues?q=is%3Aopen+is%3Aissue+label%3A%22Help+Wanted%22)\n<details><summary>Upwork Automation - Do Not Edit</summary>\n    <ul>\n        <li>Upwork Job URL: https://www.upwork.com/jobs/~021973727588446180145</li>\n        <li>Upwork Job ID: 1973727588446180145</li>\n        <li>Last Price Increase: 2025-10-02</li>\n    </ul>\n</details>\n\n<details><summary>Issue Owner</summary>Current Issue Owner: @jayeshmangwani</details>",
    "closed_by": null,
    "reactions": {
      "url": "https://api.github.com/repos/Expensify/App/issues/71745/reactions",
      "total_count": 0,
      "+1": 0,
      "-1": 0,
      "laugh": 0,
      "hooray": 0,
      "confused": 0,
      "heart": 0,
      "rocket": 0,
      "eyes": 0
    },
    "timeline_url": "https://api.github.com/repos/Expensify/App/issues/71745/timeline",
    "performed_via_github_app": null,
    "state_reason": null
  },
  {
    "url": "https://api.github.com/repos/Expensify/App/issues/71723",
    "repository_url": "https://api.github.com/repos/Expensify/App",
    "labels_url": "https://api.github.com/repos/Expensify/App/issues/71723/labels{/name}",
    "comments_url": "https://api.github.com/repos/Expensify/App/issues/71723/comments",
    "events_url": "https://api.github.com/repos/Expensify/App/issues/71723/events",
    "html_url": "https://github.com/Expensify/App/issues/71723",
    "id": 3475774856,
    "node_id": "I_kwDOEQqHYc7PLB2I",
    "number": 71723,
    "title": "[$250] Invoice-Wrong recipient when selecting an email address after selecting an Invoice room",
    "user": {
      "login": "mitarachim",
      "id": 181838622,
      "node_id": "U_kgDOCtajHg",
      "avatar_url": "https://avatars.githubusercontent.com/u/181838622?v=4",
      "gravatar_id": "",
      "url": "https://api.github.com/users/mitarachim",
      "html_url": "https://github.com/mitarachim",
      "followers_url": "https://api.github.com/users/mitarachim/followers",
      "following_url": "https://api.github.com/users/mitarachim/following{/other_user}",
      "gists_url": "https://api.github.com/users/mitarachim/gists{/gist_id}",
      "starred_url": "https://api.github.com/users/mitarachim/starred{/owner}{/repo}",
      "subscriptions_url": "https://api.github.com/users/mitarachim/subscriptions",
      "organizations_url": "https://api.github.com/users/mitarachim/orgs",
      "repos_url": "https://api.github.com/users/mitarachim/repos",
      "events_url": "https://api.github.com/users/mitarachim/events{/privacy}",
      "received_events_url": "https://api.github.com/users/mitarachim/received_events",
      "type": "User",
      "user_view_type": "public",
      "site_admin": false
    },
    "labels": [
      {
        "id": 2873246102,
        "node_id": "MDU6TGFiZWwyODczMjQ2MTAy",
        "url": "https://api.github.com/repos/Expensify/App/labels/External",
        "name": "External",
        "color": "a7b8ef",
        "default": false,
        "description": "Added to denote the issue can be worked on by a contributor"
      },
      {
        "id": 2893455829,
        "node_id": "MDU6TGFiZWwyODkzNDU1ODI5",
        "url": "https://api.github.com/repos/Expensify/App/labels/Daily",
        "name": "Daily",
        "color": "eb6420",
        "default": false,
        "description": "KSv2"
      },
      {
        "id": 3136662525,
        "node_id": "MDU6TGFiZWwzMTM2NjYyNTI1",
        "url": "https://api.github.com/repos/Expensify/App/labels/Help%20Wanted",
        "name": "Help Wanted",
        "color": "CFC8F1",
        "default": false,
        "description": "Apply this label when an issue is open to proposals by contributors"
      },
      {
        "id": 4664850679,
        "node_id": "LA_kwDOEQqHYc8AAAABFgv49w",
        "url": "https://api.github.com/repos/Expensify/App/labels/Bug",
        "name": "Bug",
        "color": "93074F",
        "default": false,
        "description": "Something is broken. Auto assigns a BugZero manager."
      }
    ],
    "state": "open",
    "locked": false,
    "assignee": {
      "login": "dylanexpensify",
      "id": 60117248,
      "node_id": "MDQ6VXNlcjYwMTE3MjQ4",
      "avatar_url": "https://avatars.githubusercontent.com/u/60117248?v=4",
      "gravatar_id": "",
      "url": "https://api.github.com/users/dylanexpensify",
      "html_url": "https://github.com/dylanexpensify",
      "followers_url": "https://api.github.com/users/dylanexpensify/followers",
      "following_url": "https://api.github.com/users/dylanexpensify/following{/other_user}",
      "gists_url": "https://api.github.com/users/dylanexpensify/gists{/gist_id}",
      "starred_url": "https://api.github.com/users/dylanexpensify/starred{/owner}{/repo}",
      "subscriptions_url": "https://api.github.com/users/dylanexpensify/subscriptions",
      "organizations_url": "https://api.github.com/users/dylanexpensify/orgs",
      "repos_url": "https://api.github.com/users/dylanexpensify/repos",
      "events_url": "https://api.github.com/users/dylanexpensify/events{/privacy}",
      "received_events_url": "https://api.github.com/users/dylanexpensify/received_events",
      "type": "User",
      "user_view_type": "public",
      "site_admin": false
    },
    "assignees": [
      {
        "login": "dylanexpensify",
        "id": 60117248,
        "node_id": "MDQ6VXNlcjYwMTE3MjQ4",
        "avatar_url": "https://avatars.githubusercontent.com/u/60117248?v=4",
        "gravatar_id": "",
        "url": "https://api.github.com/users/dylanexpensify",
        "html_url": "https://github.com/dylanexpensify",
        "followers_url": "https://api.github.com/users/dylanexpensify/followers",
        "following_url": "https://api.github.com/users/dylanexpensify/following{/other_user}",
        "gists_url": "https://api.github.com/users/dylanexpensify/gists{/gist_id}",
        "starred_url": "https://api.github.com/users/dylanexpensify/starred{/owner}{/repo}",
        "subscriptions_url": "https://api.github.com/users/dylanexpensify/subscriptions",
        "organizations_url": "https://api.github.com/users/dylanexpensify/orgs",
        "repos_url": "https://api.github.com/users/dylanexpensify/repos",
        "events_url": "https://api.github.com/users/dylanexpensify/events{/privacy}",
        "received_events_url": "https://api.github.com/users/dylanexpensify/received_events",
        "type": "User",
        "user_view_type": "public",
        "site_admin": false
      },
      {
        "login": "DylanDylann",
        "id": 141406735,
        "node_id": "U_kgDOCG2yDw",
        "avatar_url": "https://avatars.githubusercontent.com/u/141406735?v=4",
        "gravatar_id": "",
        "url": "https://api.github.com/users/DylanDylann",
        "html_url": "https://github.com/DylanDylann",
        "followers_url": "https://api.github.com/users/DylanDylann/followers",
        "following_url": "https://api.github.com/users/DylanDylann/following{/other_user}",
        "gists_url": "https://api.github.com/users/DylanDylann/gists{/gist_id}",
        "starred_url": "https://api.github.com/users/DylanDylann/starred{/owner}{/repo}",
        "subscriptions_url": "https://api.github.com/users/DylanDylann/subscriptions",
        "organizations_url": "https://api.github.com/users/DylanDylann/orgs",
        "repos_url": "https://api.github.com/users/DylanDylann/repos",
        "events_url": "https://api.github.com/users/DylanDylann/events{/privacy}",
        "received_events_url": "https://api.github.com/users/DylanDylann/received_events",
        "type": "User",
        "user_view_type": "public",
        "site_admin": false
      }
    ],
    "milestone": null,
    "comments": 5,
    "created_at": "2025-10-02T02:38:22Z",
    "updated_at": "2025-10-02T08:22:12Z",
    "closed_at": null,
    "author_association": "NONE",
    "type": null,
    "active_lock_reason": null,
    "sub_issues_summary": {
      "total": 0,
      "completed": 0,
      "percent_completed": 0
    },
    "issue_dependencies_summary": {
      "blocked_by": 0,
      "total_blocked_by": 0,
      "blocking": 0,
      "total_blocking": 0
    },
    "body": "If you haven’t already, check out our [contributing guidelines](https://github.com/Expensify/ReactNativeChat/blob/main/contributingGuides/CONTRIBUTING.md) for onboarding and email contributors@expensify.com to request to join our Slack channel!\n___\n\n**Version Number:** v9.2.21-3\n**Reproducible in staging?:** Yes\n**Reproducible in production?:** Yes\n**If this was caught during regression testing, add the test name, ID and link from TestRail:** Found when working on https://github.com/Expensify/App/pull/71648\n**Email or phone of affected tester (no customers):** agexptest+pr0110@gmail.com\n**Issue reported by:** Applause Internal Team\n**Device used:** Windows 11/ Chrome, Samsung S23FE/ Android 15, iPhone 13 Mini/ iOS 18.5\n**App Component:** Other\n\n## Action Performed:\nPreconditions: Have a workspace with the Invoices feature enabled.\nHave at least one Invoice room.\n\n1. Go to staging.new.expensify.com\n2. Open FAB > Send invoice\n3. Enter amount > Next\n4. Select an Invoice room from Recents\n5. In the \"To\" field, click on the right caret icon\n6. Enter an email address that is not included in any Invoice room with the current user\n7 Send the invoice\n\n## Expected Result:\nThe app creates the invoice thread in a new Invoice room with the email address entered in step 6.\n\n## Actual Result:\nThe app creates the invoice thread in the Invoice room selected in step 4.\n\n## Workaround:\nUnknown\n\n## Platforms:\n- [x] Android: App\n- [x] Android: mWeb Chrome\n- [x] iOS: App\n- [x] iOS: mWeb Safari\n- [x] iOS: mWeb Chrome\n- [x] Windows: Chrome\n- [x] MacOS: Chrome / Safari\n- [ ] MacOS: Desktop\n\n## Screenshots/Videos\n\nhttps://github.com/user-attachments/assets/a778754b-769f-44d2-80d3-04a42a96b49d\n\n[View all open jobs on GitHub](https://github.com/Expensify/App/issues?q=is%3Aopen+is%3Aissue+label%3A%22Help+Wanted%22)\n<details><summary>Upwork Automation - Do Not Edit</summary>\n    <ul>\n        <li>Upwork Job URL: https://www.upwork.com/jobs/~021973664764145064677</li>\n        <li>Upwork Job ID: 1973664764145064677</li>\n        <li>Last Price Increase: 2025-10-02</li>\n    </ul>\n</details>\n\n<details><summary>Issue Owner</summary>Current Issue Owner: @DylanDylann</details>",
    "closed_by": null,
    "reactions": {
      "url": "https://api.github.com/repos/Expensify/App/issues/71723/reactions",
      "total_count": 0,
      "+1": 0,
      "-1": 0,
      "laugh": 0,
      "hooray": 0,
      "confused": 0,
      "heart": 0,
      "rocket": 0,
      "eyes": 0
    },
    "timeline_url": "https://api.github.com/repos/Expensify/App/issues/71723/timeline",
    "performed_via_github_app": null,
    "state_reason": null
  },
  {
    "url": "https://api.github.com/repos/Expensify/App/issues/71697",
    "repository_url": "https://api.github.com/repos/Expensify/App",
    "labels_url": "https://api.github.com/repos/Expensify/App/issues/71697/labels{/name}",
    "comments_url": "https://api.github.com/repos/Expensify/App/issues/71697/comments",
    "events_url": "https://api.github.com/repos/Expensify/App/issues/71697/events",
    "html_url": "https://github.com/Expensify/App/issues/71697",
    "id": 3474473126,
    "node_id": "I_kwDOEQqHYc7PGECm",
    "number": 71697,
    "title": "[$250] BA - Error is shown when moving back to step 1 and clicking Next in enable Wallet flow",
    "user": {
      "login": "lanitochka17",
      "id": 78819774,
      "node_id": "MDQ6VXNlcjc4ODE5Nzc0",
      "avatar_url": "https://avatars.githubusercontent.com/u/78819774?v=4",
      "gravatar_id": "",
      "url": "https://api.github.com/users/lanitochka17",
      "html_url": "https://github.com/lanitochka17",
      "followers_url": "https://api.github.com/users/lanitochka17/followers",
      "following_url": "https://api.github.com/users/lanitochka17/following{/other_user}",
      "gists_url": "https://api.github.com/users/lanitochka17/gists{/gist_id}",
      "starred_url": "https://api.github.com/users/lanitochka17/starred{/owner}{/repo}",
      "subscriptions_url": "https://api.github.com/users/lanitochka17/subscriptions",
      "organizations_url": "https://api.github.com/users/lanitochka17/orgs",
      "repos_url": "https://api.github.com/users/lanitochka17/repos",
      "events_url": "https://api.github.com/users/lanitochka17/events{/privacy}",
      "received_events_url": "https://api.github.com/users/lanitochka17/received_events",
      "type": "User",
      "user_view_type": "public",
      "site_admin": false
    },
    "labels": [
      {
        "id": 2873246102,
        "node_id": "MDU6TGFiZWwyODczMjQ2MTAy",
        "url": "https://api.github.com/repos/Expensify/App/labels/External",
        "name": "External",
        "color": "a7b8ef",
        "default": false,
        "description": "Added to denote the issue can be worked on by a contributor"
      },
      {
        "id": 2873635554,
        "node_id": "MDU6TGFiZWwyODczNjM1NTU0",
        "url": "https://api.github.com/repos/Expensify/App/labels/Engineering",
        "name": "Engineering",
        "color": "274073",
        "default": false,
        "description": ""
      },
      {
        "id": 2893455829,
        "node_id": "MDU6TGFiZWwyODkzNDU1ODI5",
        "url": "https://api.github.com/repos/Expensify/App/labels/Daily",
        "name": "Daily",
        "color": "eb6420",
        "default": false,
        "description": "KSv2"
      },
      {
        "id": 4664850679,
        "node_id": "LA_kwDOEQqHYc8AAAABFgv49w",
        "url": "https://api.github.com/repos/Expensify/App/labels/Bug",
        "name": "Bug",
        "color": "93074F",
        "default": false,
        "description": "Something is broken. Auto assigns a BugZero manager."
      }
    ],
    "state": "open",
    "locked": false,
    "assignee": {
      "login": "marcochavezf",
      "id": 6829422,
      "node_id": "MDQ6VXNlcjY4Mjk0MjI=",
      "avatar_url": "https://avatars.githubusercontent.com/u/6829422?v=4",
      "gravatar_id": "",
      "url": "https://api.github.com/users/marcochavezf",
      "html_url": "https://github.com/marcochavezf",
      "followers_url": "https://api.github.com/users/marcochavezf/followers",
      "following_url": "https://api.github.com/users/marcochavezf/following{/other_user}",
      "gists_url": "https://api.github.com/users/marcochavezf/gists{/gist_id}",
      "starred_url": "https://api.github.com/users/marcochavezf/starred{/owner}{/repo}",
      "subscriptions_url": "https://api.github.com/users/marcochavezf/subscriptions",
      "organizations_url": "https://api.github.com/users/marcochavezf/orgs",
      "repos_url": "https://api.github.com/users/marcochavezf/repos",
      "events_url": "https://api.github.com/users/marcochavezf/events{/privacy}",
      "received_events_url": "https://api.github.com/users/marcochavezf/received_events",
      "type": "User",
      "user_view_type": "public",
      "site_admin": false
    },
    "assignees": [
      {
        "login": "marcochavezf",
        "id": 6829422,
        "node_id": "MDQ6VXNlcjY4Mjk0MjI=",
        "avatar_url": "https://avatars.githubusercontent.com/u/6829422?v=4",
        "gravatar_id": "",
        "url": "https://api.github.com/users/marcochavezf",
        "html_url": "https://github.com/marcochavezf",
        "followers_url": "https://api.github.com/users/marcochavezf/followers",
        "following_url": "https://api.github.com/users/marcochavezf/following{/other_user}",
        "gists_url": "https://api.github.com/users/marcochavezf/gists{/gist_id}",
        "starred_url": "https://api.github.com/users/marcochavezf/starred{/owner}{/repo}",
        "subscriptions_url": "https://api.github.com/users/marcochavezf/subscriptions",
        "organizations_url": "https://api.github.com/users/marcochavezf/orgs",
        "repos_url": "https://api.github.com/users/marcochavezf/repos",
        "events_url": "https://api.github.com/users/marcochavezf/events{/privacy}",
        "received_events_url": "https://api.github.com/users/marcochavezf/received_events",
        "type": "User",
        "user_view_type": "public",
        "site_admin": false
      },
      {
        "login": "joekaufmanexpensify",
        "id": 54866469,
        "node_id": "MDQ6VXNlcjU0ODY2NDY5",
        "avatar_url": "https://avatars.githubusercontent.com/u/54866469?v=4",
        "gravatar_id": "",
        "url": "https://api.github.com/users/joekaufmanexpensify",
        "html_url": "https://github.com/joekaufmanexpensify",
        "followers_url": "https://api.github.com/users/joekaufmanexpensify/followers",
        "following_url": "https://api.github.com/users/joekaufmanexpensify/following{/other_user}",
        "gists_url": "https://api.github.com/users/joekaufmanexpensify/gists{/gist_id}",
        "starred_url": "https://api.github.com/users/joekaufmanexpensify/starred{/owner}{/repo}",
        "subscriptions_url": "https://api.github.com/users/joekaufmanexpensify/subscriptions",
        "organizations_url": "https://api.github.com/users/joekaufmanexpensify/orgs",
        "repos_url": "https://api.github.com/users/joekaufmanexpensify/repos",
        "events_url": "https://api.github.com/users/joekaufmanexpensify/events{/privacy}",
        "received_events_url": "https://api.github.com/users/joekaufmanexpensify/received_events",
        "type": "User",
        "user_view_type": "public",
        "site_admin": false
      },
      {
        "login": "dominictb",
        "id": 165644294,
        "node_id": "U_kgDOCd-IBg",
        "avatar_url": "https://avatars.githubusercontent.com/u/165644294?v=4",
        "gravatar_id": "",
        "url": "https://api.github.com/users/dominictb",
        "html_url": "https://github.com/dominictb",
        "followers_url": "https://api.github.com/users/dominictb/followers",
        "following_url": "https://api.github.com/users/dominictb/following{/other_user}",
        "gists_url": "https://api.github.com/users/dominictb/gists{/gist_id}",
        "starred_url": "https://api.github.com/users/dominictb/starred{/owner}{/repo}",
        "subscriptions_url": "https://api.github.com/users/dominictb/subscriptions",
        "organizations_url": "https://api.github.com/users/dominictb/orgs",
        "repos_url": "https://api.github.com/users/dominictb/repos",
        "events_url": "https://api.github.com/users/dominictb/events{/privacy}",
        "received_events_url": "https://api.github.com/users/dominictb/received_events",
        "type": "User",
        "user_view_type": "public",
        "site_admin": false
      }
    ],
    "milestone": null,
    "comments": 24,
    "created_at": "2025-10-01T17:33:27Z",
    "updated_at": "2025-10-01T21:21:34Z",
    "closed_at": null,
    "author_association": "NONE",
    "type": null,
    "active_lock_reason": null,
    "sub_issues_summary": {
      "total": 0,
      "completed": 0,
      "percent_completed": 0
    },
    "issue_dependencies_summary": {
      "blocked_by": 0,
      "total_blocked_by": 0,
      "blocking": 0,
      "total_blocking": 0
    },
    "body": "If you haven’t already, check out our [contributing guidelines](https://github.com/Expensify/ReactNativeChat/blob/main/contributingGuides/CONTRIBUTING.md) for onboarding and email contributors@expensify.com to request to join our Slack channel!\n___\n\n**Version Number:** 9.2.21-2\n**Reproducible in staging?:** Y\n**Reproducible in production?:** Unable to validate in Prod\n**If this was caught during regression testing, add the test name, ID and link from TestRail:** https://github.com/Expensify/App/pull/70878\n**Issue reported by:** Applause - Internal Team\n\n\n## Action Performed:\n1. Sign in to ND with a new account, verify the account\n2. Navigate to Wallet, click Enable Wallet\n3. Press \"Add bank account\" green button, continue with the Regions bank\n4. When back in ND, on \"Choose your bank account\" RHP select \"Plaid Saving\", click Next\n5. Enter the name, click Next\n6. Select Date of birth, Next\n7. Click back arrow until you reached step 1\n8. On \"Choose your bank account\" RHP click Next\n9. On \"Confirm your bank account\" RHP click Confirm\n\n## Expected Result:\nUser is able to proceed with the flow, \"What's your legal name\" RHP opens\n\n## Actual Result:\nUser is not able to proceed, error \"Bank account can't be created, it looks like a bank account with the same information already exists in your account.\" is displayed. After refreshing the page User is finally moved to the next step\n\n## Workaround:\nUnknown\n\n## Platforms:\nSelect the officially supported platforms where the issue was reproduced:\n- [ ] Android: App\n- [ ] Android: mWeb Chrome\n- [x] iOS: App\n- [ ] iOS: mWeb Safari\n- [ ] iOS: mWeb Chrome\n- [x] Windows: Chrome\n- [x] MacOS: Chrome / Safari\n- [x] MacOS: Desktop\n\n<details>\n  <summary>Platforms Tested:</summary>\nOn which of our officially supported platforms was this issue tested:\n\n- [ ] Android: App\n- [ ] Android: mWeb Chrome\n- [ ] iOS: App\n- [ ] iOS: mWeb Safari\n- [ ] iOS: mWeb Chrome\n- [ ] Windows: Chrome\n- [ ] MacOS: Chrome / Safari\n- [ ] MacOS: Desktop\n\n</details>\n\n## Screenshots/Videos\n\n<details>\n  <summary>Add any screenshot/video evidence</summary>\n\n\n</details> \n\nhttps://github.com/user-attachments/assets/af647fa5-3d6c-4298-af7b-b673cdd3062c\n\n[View all open jobs on GitHub](https://github.com/Expensify/App/issues?q=is%3Aopen+is%3Aissue+label%3A%22Help+Wanted%22)\n\n<details><summary>Upwork Automation - Do Not Edit</summary>\n    <ul>\n        <li>Upwork Job URL: https://www.upwork.com/jobs/~021973441732615410481</li>\n        <li>Upwork Job ID: 1973441732615410481</li>\n        <li>Last Price Increase: 2025-10-01</li>\n<li>Automatic offers: </li>\n<ul>\n<li>dominictb | Contributor | 108974773</li>\n</ul></li>\n    </ul>\n</details>\n\n<details><summary>Issue Owner</summary>Current Issue Owner: @rushatgabhane</details>",
    "closed_by": null,
    "reactions": {
      "url": "https://api.github.com/repos/Expensify/App/issues/71697/reactions",
      "total_count": 0,
      "+1": 0,
      "-1": 0,
      "laugh": 0,
      "hooray": 0,
      "confused": 0,
      "heart": 0,
      "rocket": 0,
      "eyes": 0
    },
    "timeline_url": "https://api.github.com/repos/Expensify/App/issues/71697/timeline",
    "performed_via_github_app": null,
    "state_reason": null
  },
  {
    "url": "https://api.github.com/repos/Expensify/App/issues/71693",
    "repository_url": "https://api.github.com/repos/Expensify/App",
    "labels_url": "https://api.github.com/repos/Expensify/App/issues/71693/labels{/name}",
    "comments_url": "https://api.github.com/repos/Expensify/App/issues/71693/comments",
    "events_url": "https://api.github.com/repos/Expensify/App/issues/71693/events",
    "html_url": "https://github.com/Expensify/App/issues/71693",
    "id": 3474403893,
    "node_id": "I_kwDOEQqHYc7PFzI1",
    "number": 71693,
    "title": "[$250] BA - Clicking Next on Choose your BA account verification page leads to Add bank account",
    "user": {
      "login": "lanitochka17",
      "id": 78819774,
      "node_id": "MDQ6VXNlcjc4ODE5Nzc0",
      "avatar_url": "https://avatars.githubusercontent.com/u/78819774?v=4",
      "gravatar_id": "",
      "url": "https://api.github.com/users/lanitochka17",
      "html_url": "https://github.com/lanitochka17",
      "followers_url": "https://api.github.com/users/lanitochka17/followers",
      "following_url": "https://api.github.com/users/lanitochka17/following{/other_user}",
      "gists_url": "https://api.github.com/users/lanitochka17/gists{/gist_id}",
      "starred_url": "https://api.github.com/users/lanitochka17/starred{/owner}{/repo}",
      "subscriptions_url": "https://api.github.com/users/lanitochka17/subscriptions",
      "organizations_url": "https://api.github.com/users/lanitochka17/orgs",
      "repos_url": "https://api.github.com/users/lanitochka17/repos",
      "events_url": "https://api.github.com/users/lanitochka17/events{/privacy}",
      "received_events_url": "https://api.github.com/users/lanitochka17/received_events",
      "type": "User",
      "user_view_type": "public",
      "site_admin": false
    },
    "labels": [
      {
        "id": 2873246102,
        "node_id": "MDU6TGFiZWwyODczMjQ2MTAy",
        "url": "https://api.github.com/repos/Expensify/App/labels/External",
        "name": "External",
        "color": "a7b8ef",
        "default": false,
        "description": "Added to denote the issue can be worked on by a contributor"
      },
      {
        "id": 2873635554,
        "node_id": "MDU6TGFiZWwyODczNjM1NTU0",
        "url": "https://api.github.com/repos/Expensify/App/labels/Engineering",
        "name": "Engineering",
        "color": "274073",
        "default": false,
        "description": ""
      },
      {
        "id": 2893455829,
        "node_id": "MDU6TGFiZWwyODkzNDU1ODI5",
        "url": "https://api.github.com/repos/Expensify/App/labels/Daily",
        "name": "Daily",
        "color": "eb6420",
        "default": false,
        "description": "KSv2"
      },
      {
        "id": 3136662525,
        "node_id": "MDU6TGFiZWwzMTM2NjYyNTI1",
        "url": "https://api.github.com/repos/Expensify/App/labels/Help%20Wanted",
        "name": "Help Wanted",
        "color": "CFC8F1",
        "default": false,
        "description": "Apply this label when an issue is open to proposals by contributors"
      },
      {
        "id": 4664850679,
        "node_id": "LA_kwDOEQqHYc8AAAABFgv49w",
        "url": "https://api.github.com/repos/Expensify/App/labels/Bug",
        "name": "Bug",
        "color": "93074F",
        "default": false,
        "description": "Something is broken. Auto assigns a BugZero manager."
      }
    ],
    "state": "open",
    "locked": false,
    "assignee": {
      "login": "heyjennahay",
      "id": 12088484,
      "node_id": "MDQ6VXNlcjEyMDg4NDg0",
      "avatar_url": "https://avatars.githubusercontent.com/u/12088484?v=4",
      "gravatar_id": "",
      "url": "https://api.github.com/users/heyjennahay",
      "html_url": "https://github.com/heyjennahay",
      "followers_url": "https://api.github.com/users/heyjennahay/followers",
      "following_url": "https://api.github.com/users/heyjennahay/following{/other_user}",
      "gists_url": "https://api.github.com/users/heyjennahay/gists{/gist_id}",
      "starred_url": "https://api.github.com/users/heyjennahay/starred{/owner}{/repo}",
      "subscriptions_url": "https://api.github.com/users/heyjennahay/subscriptions",
      "organizations_url": "https://api.github.com/users/heyjennahay/orgs",
      "repos_url": "https://api.github.com/users/heyjennahay/repos",
      "events_url": "https://api.github.com/users/heyjennahay/events{/privacy}",
      "received_events_url": "https://api.github.com/users/heyjennahay/received_events",
      "type": "User",
      "user_view_type": "public",
      "site_admin": false
    },
    "assignees": [
      {
        "login": "heyjennahay",
        "id": 12088484,
        "node_id": "MDQ6VXNlcjEyMDg4NDg0",
        "avatar_url": "https://avatars.githubusercontent.com/u/12088484?v=4",
        "gravatar_id": "",
        "url": "https://api.github.com/users/heyjennahay",
        "html_url": "https://github.com/heyjennahay",
        "followers_url": "https://api.github.com/users/heyjennahay/followers",
        "following_url": "https://api.github.com/users/heyjennahay/following{/other_user}",
        "gists_url": "https://api.github.com/users/heyjennahay/gists{/gist_id}",
        "starred_url": "https://api.github.com/users/heyjennahay/starred{/owner}{/repo}",
        "subscriptions_url": "https://api.github.com/users/heyjennahay/subscriptions",
        "organizations_url": "https://api.github.com/users/heyjennahay/orgs",
        "repos_url": "https://api.github.com/users/heyjennahay/repos",
        "events_url": "https://api.github.com/users/heyjennahay/events{/privacy}",
        "received_events_url": "https://api.github.com/users/heyjennahay/received_events",
        "type": "User",
        "user_view_type": "public",
        "site_admin": false
      },
      {
        "login": "blimpich",
        "id": 17171674,
        "node_id": "MDQ6VXNlcjE3MTcxNjc0",
        "avatar_url": "https://avatars.githubusercontent.com/u/17171674?v=4",
        "gravatar_id": "",
        "url": "https://api.github.com/users/blimpich",
        "html_url": "https://github.com/blimpich",
        "followers_url": "https://api.github.com/users/blimpich/followers",
        "following_url": "https://api.github.com/users/blimpich/following{/other_user}",
        "gists_url": "https://api.github.com/users/blimpich/gists{/gist_id}",
        "starred_url": "https://api.github.com/users/blimpich/starred{/owner}{/repo}",
        "subscriptions_url": "https://api.github.com/users/blimpich/subscriptions",
        "organizations_url": "https://api.github.com/users/blimpich/orgs",
        "repos_url": "https://api.github.com/users/blimpich/repos",
        "events_url": "https://api.github.com/users/blimpich/events{/privacy}",
        "received_events_url": "https://api.github.com/users/blimpich/received_events",
        "type": "User",
        "user_view_type": "public",
        "site_admin": false
      },
      {
        "login": "shubham1206agra",
        "id": 58412969,
        "node_id": "MDQ6VXNlcjU4NDEyOTY5",
        "avatar_url": "https://avatars.githubusercontent.com/u/58412969?v=4",
        "gravatar_id": "",
        "url": "https://api.github.com/users/shubham1206agra",
        "html_url": "https://github.com/shubham1206agra",
        "followers_url": "https://api.github.com/users/shubham1206agra/followers",
        "following_url": "https://api.github.com/users/shubham1206agra/following{/other_user}",
        "gists_url": "https://api.github.com/users/shubham1206agra/gists{/gist_id}",
        "starred_url": "https://api.github.com/users/shubham1206agra/starred{/owner}{/repo}",
        "subscriptions_url": "https://api.github.com/users/shubham1206agra/subscriptions",
        "organizations_url": "https://api.github.com/users/shubham1206agra/orgs",
        "repos_url": "https://api.github.com/users/shubham1206agra/repos",
        "events_url": "https://api.github.com/users/shubham1206agra/events{/privacy}",
        "received_events_url": "https://api.github.com/users/shubham1206agra/received_events",
        "type": "User",
        "user_view_type": "public",
        "site_admin": false
      }
    ],
    "milestone": null,
    "comments": 10,
    "created_at": "2025-10-01T17:08:15Z",
    "updated_at": "2025-10-02T07:03:46Z",
    "closed_at": null,
    "author_association": "NONE",
    "type": null,
    "active_lock_reason": null,
    "sub_issues_summary": {
      "total": 0,
      "completed": 0,
      "percent_completed": 0
    },
    "issue_dependencies_summary": {
      "blocked_by": 0,
      "total_blocked_by": 0,
      "blocking": 0,
      "total_blocking": 0
    },
    "body": "If you haven’t already, check out our [contributing guidelines](https://github.com/Expensify/ReactNativeChat/blob/main/contributingGuides/CONTRIBUTING.md) for onboarding and email contributors@expensify.com to request to join our Slack channel!\n___\n\n**Version Number:** 9.2.21-2\n**Reproducible in staging?:** Y\n**Reproducible in production?:** Unable to validate in Prod\n**If this was caught during regression testing, add the test name, ID and link from TestRail:** https://github.com/Expensify/App/pull/70878\n**Issue reported by:** Applause - Internal Team\n\n\n## Action Performed:\n1. Sign in to ND and verify the account\n2. Navigate to Wallet, click Enable Wallet\n3. Press \"Add bank account\" green button\n4. Continue with the Regions bank, enter credentials\n5. When back in ND, on \"Choose your bank account\" RHP select \"Plaid Saving\", click Next\n6. On \"Confirm your bank account\" RHP click the arrow on the right of the selected option\n7. Click Next without making any changes\n\n## Expected Result:\nUser is returned to the \"Confirm your bank account\" RHP\n\n## Actual Result:\n\"Add bank account\" RHP is displayed\n\n## Workaround:\nUnknown\n\n## Platforms:\nSelect the officially supported platforms where the issue was reproduced:\n- [ ] Android: App\n- [ ] Android: mWeb Chrome\n- [ ] iOS: App\n- [x] iOS: mWeb Safari\n- [ ] iOS: mWeb Chrome\n- [x] Windows: Chrome\n- [x] MacOS: Chrome / Safari\n- [x] MacOS: Desktop\n\n<details>\n  <summary>Platforms Tested:</summary>\nOn which of our officially supported platforms was this issue tested:\n\n- [ ] Android: App\n- [ ] Android: mWeb Chrome\n- [ ] iOS: App\n- [ ] iOS: mWeb Safari\n- [ ] iOS: mWeb Chrome\n- [ ] Windows: Chrome\n- [ ] MacOS: Chrome / Safari\n- [ ] MacOS: Desktop\n\n</details>\n\n## Screenshots/Videos\n\n<details>\n  <summary>Add any screenshot/video evidence</summary>\n\n\n</details> \n\nhttps://github.com/user-attachments/assets/c3a0795c-b9cd-441c-a850-ba630f7ba707\n\n[View all open jobs on GitHub](https://github.com/Expensify/App/issues?q=is%3Aopen+is%3Aissue+label%3A%22Help+Wanted%22)\n\n<details><summary>Upwork Automation - Do Not Edit</summary>\n    <ul>\n        <li>Upwork Job URL: https://www.upwork.com/jobs/~021973462372403712817</li>\n        <li>Upwork Job ID: 1973462372403712817</li>\n        <li>Last Price Increase: 2025-10-01</li>\n    </ul>\n</details>\n\n<details><summary>Issue Owner</summary>Current Issue Owner: @shubham1206agra</details>",
    "closed_by": null,
    "reactions": {
      "url": "https://api.github.com/repos/Expensify/App/issues/71693/reactions",
      "total_count": 0,
      "+1": 0,
      "-1": 0,
      "laugh": 0,
      "hooray": 0,
      "confused": 0,
      "heart": 0,
      "rocket": 0,
      "eyes": 0
    },
    "timeline_url": "https://api.github.com/repos/Expensify/App/issues/71693/timeline",
    "performed_via_github_app": null,
    "state_reason": null
  },
  {
    "url": "https://api.github.com/repos/Expensify/App/issues/71672",
    "repository_url": "https://api.github.com/repos/Expensify/App",
    "labels_url": "https://api.github.com/repos/Expensify/App/issues/71672/labels{/name}",
    "comments_url": "https://api.github.com/repos/Expensify/App/issues/71672/comments",
    "events_url": "https://api.github.com/repos/Expensify/App/issues/71672/events",
    "html_url": "https://github.com/Expensify/App/issues/71672",
    "id": 3473631955,
    "node_id": "I_kwDOEQqHYc7PC2rT",
    "number": 71672,
    "title": "[$250] App shortcut - Create manual expense flow opens when launching app via Log distance shortcut",
    "user": {
      "login": "mitarachim",
      "id": 181838622,
      "node_id": "U_kgDOCtajHg",
      "avatar_url": "https://avatars.githubusercontent.com/u/181838622?v=4",
      "gravatar_id": "",
      "url": "https://api.github.com/users/mitarachim",
      "html_url": "https://github.com/mitarachim",
      "followers_url": "https://api.github.com/users/mitarachim/followers",
      "following_url": "https://api.github.com/users/mitarachim/following{/other_user}",
      "gists_url": "https://api.github.com/users/mitarachim/gists{/gist_id}",
      "starred_url": "https://api.github.com/users/mitarachim/starred{/owner}{/repo}",
      "subscriptions_url": "https://api.github.com/users/mitarachim/subscriptions",
      "organizations_url": "https://api.github.com/users/mitarachim/orgs",
      "repos_url": "https://api.github.com/users/mitarachim/repos",
      "events_url": "https://api.github.com/users/mitarachim/events{/privacy}",
      "received_events_url": "https://api.github.com/users/mitarachim/received_events",
      "type": "User",
      "user_view_type": "public",
      "site_admin": false
    },
    "labels": [
      {
        "id": 2873246102,
        "node_id": "MDU6TGFiZWwyODczMjQ2MTAy",
        "url": "https://api.github.com/repos/Expensify/App/labels/External",
        "name": "External",
        "color": "a7b8ef",
        "default": false,
        "description": "Added to denote the issue can be worked on by a contributor"
      },
      {
        "id": 2893455829,
        "node_id": "MDU6TGFiZWwyODkzNDU1ODI5",
        "url": "https://api.github.com/repos/Expensify/App/labels/Daily",
        "name": "Daily",
        "color": "eb6420",
        "default": false,
        "description": "KSv2"
      },
      {
        "id": 3136662525,
        "node_id": "MDU6TGFiZWwzMTM2NjYyNTI1",
        "url": "https://api.github.com/repos/Expensify/App/labels/Help%20Wanted",
        "name": "Help Wanted",
        "color": "CFC8F1",
        "default": false,
        "description": "Apply this label when an issue is open to proposals by contributors"
      },
      {
        "id": 4664850679,
        "node_id": "LA_kwDOEQqHYc8AAAABFgv49w",
        "url": "https://api.github.com/repos/Expensify/App/labels/Bug",
        "name": "Bug",
        "color": "93074F",
        "default": false,
        "description": "Something is broken. Auto assigns a BugZero manager."
      }
    ],
    "state": "open",
    "locked": false,
    "assignee": {
      "login": "jliexpensify",
      "id": 30815269,
      "node_id": "MDQ6VXNlcjMwODE1MjY5",
      "avatar_url": "https://avatars.githubusercontent.com/u/30815269?v=4",
      "gravatar_id": "",
      "url": "https://api.github.com/users/jliexpensify",
      "html_url": "https://github.com/jliexpensify",
      "followers_url": "https://api.github.com/users/jliexpensify/followers",
      "following_url": "https://api.github.com/users/jliexpensify/following{/other_user}",
      "gists_url": "https://api.github.com/users/jliexpensify/gists{/gist_id}",
      "starred_url": "https://api.github.com/users/jliexpensify/starred{/owner}{/repo}",
      "subscriptions_url": "https://api.github.com/users/jliexpensify/subscriptions",
      "organizations_url": "https://api.github.com/users/jliexpensify/orgs",
      "repos_url": "https://api.github.com/users/jliexpensify/repos",
      "events_url": "https://api.github.com/users/jliexpensify/events{/privacy}",
      "received_events_url": "https://api.github.com/users/jliexpensify/received_events",
      "type": "User",
      "user_view_type": "public",
      "site_admin": false
    },
    "assignees": [
      {
        "login": "jliexpensify",
        "id": 30815269,
        "node_id": "MDQ6VXNlcjMwODE1MjY5",
        "avatar_url": "https://avatars.githubusercontent.com/u/30815269?v=4",
        "gravatar_id": "",
        "url": "https://api.github.com/users/jliexpensify",
        "html_url": "https://github.com/jliexpensify",
        "followers_url": "https://api.github.com/users/jliexpensify/followers",
        "following_url": "https://api.github.com/users/jliexpensify/following{/other_user}",
        "gists_url": "https://api.github.com/users/jliexpensify/gists{/gist_id}",
        "starred_url": "https://api.github.com/users/jliexpensify/starred{/owner}{/repo}",
        "subscriptions_url": "https://api.github.com/users/jliexpensify/subscriptions",
        "organizations_url": "https://api.github.com/users/jliexpensify/orgs",
        "repos_url": "https://api.github.com/users/jliexpensify/repos",
        "events_url": "https://api.github.com/users/jliexpensify/events{/privacy}",
        "received_events_url": "https://api.github.com/users/jliexpensify/received_events",
        "type": "User",
        "user_view_type": "public",
        "site_admin": false
      },
      {
        "login": "dominictb",
        "id": 165644294,
        "node_id": "U_kgDOCd-IBg",
        "avatar_url": "https://avatars.githubusercontent.com/u/165644294?v=4",
        "gravatar_id": "",
        "url": "https://api.github.com/users/dominictb",
        "html_url": "https://github.com/dominictb",
        "followers_url": "https://api.github.com/users/dominictb/followers",
        "following_url": "https://api.github.com/users/dominictb/following{/other_user}",
        "gists_url": "https://api.github.com/users/dominictb/gists{/gist_id}",
        "starred_url": "https://api.github.com/users/dominictb/starred{/owner}{/repo}",
        "subscriptions_url": "https://api.github.com/users/dominictb/subscriptions",
        "organizations_url": "https://api.github.com/users/dominictb/orgs",
        "repos_url": "https://api.github.com/users/dominictb/repos",
        "events_url": "https://api.github.com/users/dominictb/events{/privacy}",
        "received_events_url": "https://api.github.com/users/dominictb/received_events",
        "type": "User",
        "user_view_type": "public",
        "site_admin": false
      }
    ],
    "milestone": null,
    "comments": 8,
    "created_at": "2025-10-01T13:41:07Z",
    "updated_at": "2025-10-02T05:03:44Z",
    "closed_at": null,
    "author_association": "NONE",
    "type": null,
    "active_lock_reason": null,
    "sub_issues_summary": {
      "total": 0,
      "completed": 0,
      "percent_completed": 0
    },
    "issue_dependencies_summary": {
      "blocked_by": 0,
      "total_blocked_by": 0,
      "blocking": 0,
      "total_blocking": 0
    },
    "body": "If you haven’t already, check out our [contributing guidelines](https://github.com/Expensify/ReactNativeChat/blob/main/contributingGuides/CONTRIBUTING.md) for onboarding and email contributors@expensify.com to request to join our Slack channel!\n___\n\n**Version Number:** 9.2.21-0\n**Reproducible in staging?:** Yes\n**Reproducible in production?:** Yes\n**If this was caught during regression testing, add the test name, ID and link from TestRail:** https://github.com/Expensify/App/pull/64056\n**Email or phone of affected tester (no customers):** applausetester+djdkskskksks@applause.expensifail.com\n**Issue reported by:** Applause Internal Team\n**Device used:** iPhone 15 Pro Max / iOS 26.0\n**App Component:** Other\n\n## Action Performed:\nPrecondition:\n- User is logged in.\n\n1. Long press on Expensify app on app home screen.\n2. Tap Log distance.\n\n## Expected Result:\nTrack distance flow will open.\n\n## Actual Result:\nCreate manual expense flow opens.\n\n## Workaround:\nUnknown\n\n## Platforms:\n- [x] Android: App\n- [ ] Android: mWeb Chrome\n- [x] iOS: App\n- [ ] iOS: mWeb Safari\n- [ ] iOS: mWeb Chrome\n- [ ] Windows: Chrome\n- [ ] MacOS: Chrome / Safari\n- [ ] MacOS: Desktop\n\n## Screenshots/Videos\n\nhttps://github.com/user-attachments/assets/9e6a2802-989a-43ec-9f77-13f2e6fff81e\n\n[View all open jobs on GitHub](https://github.com/Expensify/App/issues?q=is%3Aopen+is%3Aissue+label%3A%22Help+Wanted%22)\n<details><summary>Upwork Automation - Do Not Edit</summary>\n    <ul>\n        <li>Upwork Job URL: https://www.upwork.com/jobs/~021973614816427393780</li>\n        <li>Upwork Job ID: 1973614816427393780</li>\n        <li>Last Price Increase: 2025-10-02</li>\n    </ul>\n</details>\n\n<details><summary>Issue Owner</summary>Current Issue Owner: @dominictb</details>",
    "closed_by": null,
    "reactions": {
      "url": "https://api.github.com/repos/Expensify/App/issues/71672/reactions",
      "total_count": 0,
      "+1": 0,
      "-1": 0,
      "laugh": 0,
      "hooray": 0,
      "confused": 0,
      "heart": 0,
      "rocket": 0,
      "eyes": 0
    },
    "timeline_url": "https://api.github.com/repos/Expensify/App/issues/71672/timeline",
    "performed_via_github_app": null,
    "state_reason": null
  },
  {
    "url": "https://api.github.com/repos/Expensify/App/issues/71665",
    "repository_url": "https://api.github.com/repos/Expensify/App",
    "labels_url": "https://api.github.com/repos/Expensify/App/issues/71665/labels{/name}",
    "comments_url": "https://api.github.com/repos/Expensify/App/issues/71665/comments",
    "events_url": "https://api.github.com/repos/Expensify/App/issues/71665/events",
    "html_url": "https://github.com/Expensify/App/issues/71665",
    "id": 3473243013,
    "node_id": "I_kwDOEQqHYc7PBXuF",
    "number": 71665,
    "title": "[$250] Expensify Card - Magic code error cannot be dismissed with X button",
    "user": {
      "login": "jponikarchuk",
      "id": 141990088,
      "node_id": "U_kgDOCHaYyA",
      "avatar_url": "https://avatars.githubusercontent.com/u/141990088?v=4",
      "gravatar_id": "",
      "url": "https://api.github.com/users/jponikarchuk",
      "html_url": "https://github.com/jponikarchuk",
      "followers_url": "https://api.github.com/users/jponikarchuk/followers",
      "following_url": "https://api.github.com/users/jponikarchuk/following{/other_user}",
      "gists_url": "https://api.github.com/users/jponikarchuk/gists{/gist_id}",
      "starred_url": "https://api.github.com/users/jponikarchuk/starred{/owner}{/repo}",
      "subscriptions_url": "https://api.github.com/users/jponikarchuk/subscriptions",
      "organizations_url": "https://api.github.com/users/jponikarchuk/orgs",
      "repos_url": "https://api.github.com/users/jponikarchuk/repos",
      "events_url": "https://api.github.com/users/jponikarchuk/events{/privacy}",
      "received_events_url": "https://api.github.com/users/jponikarchuk/received_events",
      "type": "User",
      "user_view_type": "public",
      "site_admin": false
    },
    "labels": [
      {
        "id": 2873246102,
        "node_id": "MDU6TGFiZWwyODczMjQ2MTAy",
        "url": "https://api.github.com/repos/Expensify/App/labels/External",
        "name": "External",
        "color": "a7b8ef",
        "default": false,
        "description": "Added to denote the issue can be worked on by a contributor"
      },
      {
        "id": 2893455829,
        "node_id": "MDU6TGFiZWwyODkzNDU1ODI5",
        "url": "https://api.github.com/repos/Expensify/App/labels/Daily",
        "name": "Daily",
        "color": "eb6420",
        "default": false,
        "description": "KSv2"
      },
      {
        "id": 3136662525,
        "node_id": "MDU6TGFiZWwzMTM2NjYyNTI1",
        "url": "https://api.github.com/repos/Expensify/App/labels/Help%20Wanted",
        "name": "Help Wanted",
        "color": "CFC8F1",
        "default": false,
        "description": "Apply this label when an issue is open to proposals by contributors"
      },
      {
        "id": 4664850679,
        "node_id": "LA_kwDOEQqHYc8AAAABFgv49w",
        "url": "https://api.github.com/repos/Expensify/App/labels/Bug",
        "name": "Bug",
        "color": "93074F",
        "default": false,
        "description": "Something is broken. Auto assigns a BugZero manager."
      }
    ],
    "state": "open",
    "locked": false,
    "assignee": {
      "login": "Christinadobrzyn",
      "id": 51066321,
      "node_id": "MDQ6VXNlcjUxMDY2MzIx",
      "avatar_url": "https://avatars.githubusercontent.com/u/51066321?v=4",
      "gravatar_id": "",
      "url": "https://api.github.com/users/Christinadobrzyn",
      "html_url": "https://github.com/Christinadobrzyn",
      "followers_url": "https://api.github.com/users/Christinadobrzyn/followers",
      "following_url": "https://api.github.com/users/Christinadobrzyn/following{/other_user}",
      "gists_url": "https://api.github.com/users/Christinadobrzyn/gists{/gist_id}",
      "starred_url": "https://api.github.com/users/Christinadobrzyn/starred{/owner}{/repo}",
      "subscriptions_url": "https://api.github.com/users/Christinadobrzyn/subscriptions",
      "organizations_url": "https://api.github.com/users/Christinadobrzyn/orgs",
      "repos_url": "https://api.github.com/users/Christinadobrzyn/repos",
      "events_url": "https://api.github.com/users/Christinadobrzyn/events{/privacy}",
      "received_events_url": "https://api.github.com/users/Christinadobrzyn/received_events",
      "type": "User",
      "user_view_type": "public",
      "site_admin": false
    },
    "assignees": [
      {
        "login": "akinwale",
        "id": 4160319,
        "node_id": "MDQ6VXNlcjQxNjAzMTk=",
        "avatar_url": "https://avatars.githubusercontent.com/u/4160319?v=4",
        "gravatar_id": "",
        "url": "https://api.github.com/users/akinwale",
        "html_url": "https://github.com/akinwale",
        "followers_url": "https://api.github.com/users/akinwale/followers",
        "following_url": "https://api.github.com/users/akinwale/following{/other_user}",
        "gists_url": "https://api.github.com/users/akinwale/gists{/gist_id}",
        "starred_url": "https://api.github.com/users/akinwale/starred{/owner}{/repo}",
        "subscriptions_url": "https://api.github.com/users/akinwale/subscriptions",
        "organizations_url": "https://api.github.com/users/akinwale/orgs",
        "repos_url": "https://api.github.com/users/akinwale/repos",
        "events_url": "https://api.github.com/users/akinwale/events{/privacy}",
        "received_events_url": "https://api.github.com/users/akinwale/received_events",
        "type": "User",
        "user_view_type": "public",
        "site_admin": false
      },
      {
        "login": "Christinadobrzyn",
        "id": 51066321,
        "node_id": "MDQ6VXNlcjUxMDY2MzIx",
        "avatar_url": "https://avatars.githubusercontent.com/u/51066321?v=4",
        "gravatar_id": "",
        "url": "https://api.github.com/users/Christinadobrzyn",
        "html_url": "https://github.com/Christinadobrzyn",
        "followers_url": "https://api.github.com/users/Christinadobrzyn/followers",
        "following_url": "https://api.github.com/users/Christinadobrzyn/following{/other_user}",
        "gists_url": "https://api.github.com/users/Christinadobrzyn/gists{/gist_id}",
        "starred_url": "https://api.github.com/users/Christinadobrzyn/starred{/owner}{/repo}",
        "subscriptions_url": "https://api.github.com/users/Christinadobrzyn/subscriptions",
        "organizations_url": "https://api.github.com/users/Christinadobrzyn/orgs",
        "repos_url": "https://api.github.com/users/Christinadobrzyn/repos",
        "events_url": "https://api.github.com/users/Christinadobrzyn/events{/privacy}",
        "received_events_url": "https://api.github.com/users/Christinadobrzyn/received_events",
        "type": "User",
        "user_view_type": "public",
        "site_admin": false
      }
    ],
    "milestone": null,
    "comments": 8,
    "created_at": "2025-10-01T11:53:35Z",
    "updated_at": "2025-10-01T20:15:57Z",
    "closed_at": null,
    "author_association": "NONE",
    "type": null,
    "active_lock_reason": null,
    "sub_issues_summary": {
      "total": 0,
      "completed": 0,
      "percent_completed": 0
    },
    "issue_dependencies_summary": {
      "blocked_by": 0,
      "total_blocked_by": 0,
      "blocking": 0,
      "total_blocking": 0
    },
    "body": "If you haven’t already, check out our [contributing guidelines](https://github.com/Expensify/ReactNativeChat/blob/main/contributingGuides/CONTRIBUTING.md) for onboarding and email contributors@expensify.com to request to join our Slack channel!\n___\n\n**Version Number:** 9.2.21-0\n**Reproducible in staging?:** Yes\n**Reproducible in production?:** Yes\n**If this was caught during regression testing, add the test name, ID and link from TestRail:** https://test-management.browserstack.com/projects/2219752/test-runs/TR-1103/folder/13176890/47403243/927169251\n**Email or phone of affected tester (no customers):** applausetester+011001kh@applause.expensifail.com\n**Issue reported by:** Applause Internal Team\n**Device used:** Mac 15.5 / Chrome\n**App Component:** User Settings\n\n## Action Performed:\nPrecondition:\n- User has assigned themselves a virtual card.\n\n1. Go to staging.new.expensify.com\n2. Go to Account > Wallet.\n3. Click on the virtual card.\n4. Click Reveal details.\n5. Close the RHP.\n6. Repeat Step 3 and 4 until the error \"Failed to send a new magic code. Please wait a bit and try again.\" appears.\n7. Close X button next to the message.\n\n## Expected Result:\nThe error will be dismissed.\n\n## Actual Result:\nThe magic code error cannot be dismissed with X button.\n\n## Workaround:\nUnknown\n\n## Platforms:\n- [x] Android: App\n- [x] Android: mWeb Chrome\n- [x] iOS: App\n- [x] iOS: mWeb Safari\n- [x] iOS: mWeb Chrome\n- [x] Windows: Chrome\n- [x] MacOS: Chrome / Safari\n- [x] MacOS: Desktop\n\n## Screenshots/Videos\n\nhttps://github.com/user-attachments/assets/04932400-6890-4b06-8be6-86903f0866c3\n\n[View all open jobs on GitHub](https://github.com/Expensify/App/issues?q=is%3Aopen+is%3Aissue+label%3A%22Help+Wanted%22)\n<details><summary>Upwork Automation - Do Not Edit</summary>\n    <ul>\n        <li>Upwork Job URL: https://www.upwork.com/jobs/~021973437055932896049</li>\n        <li>Upwork Job ID: 1973437055932896049</li>\n        <li>Last Price Increase: 2025-10-01</li>\n    </ul>\n</details>\n\n<details><summary>Issue Owner</summary>Current Issue Owner: @akinwale</details>",
    "closed_by": null,
    "reactions": {
      "url": "https://api.github.com/repos/Expensify/App/issues/71665/reactions",
      "total_count": 0,
      "+1": 0,
      "-1": 0,
      "laugh": 0,
      "hooray": 0,
      "confused": 0,
      "heart": 0,
      "rocket": 0,
      "eyes": 0
    },
    "timeline_url": "https://api.github.com/repos/Expensify/App/issues/71665/timeline",
    "performed_via_github_app": null,
    "state_reason": null
  },
  {
    "url": "https://api.github.com/repos/Expensify/App/issues/71658",
    "repository_url": "https://api.github.com/repos/Expensify/App",
    "labels_url": "https://api.github.com/repos/Expensify/App/issues/71658/labels{/name}",
    "comments_url": "https://api.github.com/repos/Expensify/App/issues/71658/comments",
    "events_url": "https://api.github.com/repos/Expensify/App/issues/71658/events",
    "html_url": "https://github.com/Expensify/App/issues/71658",
    "id": 3472960085,
    "node_id": "I_kwDOEQqHYc7PASpV",
    "number": 71658,
    "title": "[HOLD for payment 2025-10-02] [$250] Payment issue for E/App PR#56064",
    "user": {
      "login": "mountiny",
      "id": 36083550,
      "node_id": "MDQ6VXNlcjM2MDgzNTUw",
      "avatar_url": "https://avatars.githubusercontent.com/u/36083550?v=4",
      "gravatar_id": "",
      "url": "https://api.github.com/users/mountiny",
      "html_url": "https://github.com/mountiny",
      "followers_url": "https://api.github.com/users/mountiny/followers",
      "following_url": "https://api.github.com/users/mountiny/following{/other_user}",
      "gists_url": "https://api.github.com/users/mountiny/gists{/gist_id}",
      "starred_url": "https://api.github.com/users/mountiny/starred{/owner}{/repo}",
      "subscriptions_url": "https://api.github.com/users/mountiny/subscriptions",
      "organizations_url": "https://api.github.com/users/mountiny/orgs",
      "repos_url": "https://api.github.com/users/mountiny/repos",
      "events_url": "https://api.github.com/users/mountiny/events{/privacy}",
      "received_events_url": "https://api.github.com/users/mountiny/received_events",
      "type": "User",
      "user_view_type": "public",
      "site_admin": false
    },
    "labels": [
      {
        "id": 2873246102,
        "node_id": "MDU6TGFiZWwyODczMjQ2MTAy",
        "url": "https://api.github.com/repos/Expensify/App/labels/External",
        "name": "External",
        "color": "a7b8ef",
        "default": false,
        "description": "Added to denote the issue can be worked on by a contributor"
      },
      {
        "id": 2893455829,
        "node_id": "MDU6TGFiZWwyODkzNDU1ODI5",
        "url": "https://api.github.com/repos/Expensify/App/labels/Daily",
        "name": "Daily",
        "color": "eb6420",
        "default": false,
        "description": "KSv2"
      },
      {
        "id": 3271255930,
        "node_id": "MDU6TGFiZWwzMjcxMjU1OTMw",
        "url": "https://api.github.com/repos/Expensify/App/labels/Awaiting%20Payment",
        "name": "Awaiting Payment",
        "color": "ededed",
        "default": false,
        "description": "Auto-added when associated PR is deployed to production"
      },
      {
        "id": 4664850679,
        "node_id": "LA_kwDOEQqHYc8AAAABFgv49w",
        "url": "https://api.github.com/repos/Expensify/App/labels/Bug",
        "name": "Bug",
        "color": "93074F",
        "default": false,
        "description": "Something is broken. Auto assigns a BugZero manager."
      }
    ],
    "state": "open",
    "locked": false,
    "assignee": {
      "login": "dukenv0307",
      "id": 129500732,
      "node_id": "U_kgDOB7gGPA",
      "avatar_url": "https://avatars.githubusercontent.com/u/129500732?v=4",
      "gravatar_id": "",
      "url": "https://api.github.com/users/dukenv0307",
      "html_url": "https://github.com/dukenv0307",
      "followers_url": "https://api.github.com/users/dukenv0307/followers",
      "following_url": "https://api.github.com/users/dukenv0307/following{/other_user}",
      "gists_url": "https://api.github.com/users/dukenv0307/gists{/gist_id}",
      "starred_url": "https://api.github.com/users/dukenv0307/starred{/owner}{/repo}",
      "subscriptions_url": "https://api.github.com/users/dukenv0307/subscriptions",
      "organizations_url": "https://api.github.com/users/dukenv0307/orgs",
      "repos_url": "https://api.github.com/users/dukenv0307/repos",
      "events_url": "https://api.github.com/users/dukenv0307/events{/privacy}",
      "received_events_url": "https://api.github.com/users/dukenv0307/received_events",
      "type": "User",
      "user_view_type": "public",
      "site_admin": false
    },
    "assignees": [
      {
        "login": "twisterdotcom",
        "id": 9133401,
        "node_id": "MDQ6VXNlcjkxMzM0MDE=",
        "avatar_url": "https://avatars.githubusercontent.com/u/9133401?v=4",
        "gravatar_id": "",
        "url": "https://api.github.com/users/twisterdotcom",
        "html_url": "https://github.com/twisterdotcom",
        "followers_url": "https://api.github.com/users/twisterdotcom/followers",
        "following_url": "https://api.github.com/users/twisterdotcom/following{/other_user}",
        "gists_url": "https://api.github.com/users/twisterdotcom/gists{/gist_id}",
        "starred_url": "https://api.github.com/users/twisterdotcom/starred{/owner}{/repo}",
        "subscriptions_url": "https://api.github.com/users/twisterdotcom/subscriptions",
        "organizations_url": "https://api.github.com/users/twisterdotcom/orgs",
        "repos_url": "https://api.github.com/users/twisterdotcom/repos",
        "events_url": "https://api.github.com/users/twisterdotcom/events{/privacy}",
        "received_events_url": "https://api.github.com/users/twisterdotcom/received_events",
        "type": "User",
        "user_view_type": "public",
        "site_admin": false
      },
      {
        "login": "dukenv0307",
        "id": 129500732,
        "node_id": "U_kgDOB7gGPA",
        "avatar_url": "https://avatars.githubusercontent.com/u/129500732?v=4",
        "gravatar_id": "",
        "url": "https://api.github.com/users/dukenv0307",
        "html_url": "https://github.com/dukenv0307",
        "followers_url": "https://api.github.com/users/dukenv0307/followers",
        "following_url": "https://api.github.com/users/dukenv0307/following{/other_user}",
        "gists_url": "https://api.github.com/users/dukenv0307/gists{/gist_id}",
        "starred_url": "https://api.github.com/users/dukenv0307/starred{/owner}{/repo}",
        "subscriptions_url": "https://api.github.com/users/dukenv0307/subscriptions",
        "organizations_url": "https://api.github.com/users/dukenv0307/orgs",
        "repos_url": "https://api.github.com/users/dukenv0307/repos",
        "events_url": "https://api.github.com/users/dukenv0307/events{/privacy}",
        "received_events_url": "https://api.github.com/users/dukenv0307/received_events",
        "type": "User",
        "user_view_type": "public",
        "site_admin": false
      }
    ],
    "milestone": null,
    "comments": 4,
    "created_at": "2025-10-01T10:27:37Z",
    "updated_at": "2025-10-01T10:28:08Z",
    "closed_at": null,
    "author_association": "CONTRIBUTOR",
    "type": null,
    "active_lock_reason": null,
    "sub_issues_summary": {
      "total": 0,
      "completed": 0,
      "percent_completed": 0
    },
    "issue_dependencies_summary": {
      "blocked_by": 0,
      "total_blocked_by": 0,
      "blocking": 0,
      "total_blocking": 0
    },
    "body": "Issue created to compensate the Contributor+ member for their work on https://github.com/Expensify/App/pull/56064\nE/E issue linked to the PR - no internal issue.\nContributor+ member who reviewed the PR - @dukenv0307 .\n\nWait 7 days after the PR is deployed to production before issuing payment in case there are regressions.\n\n<details><summary>Upwork Automation - Do Not Edit</summary>\n    <ul>\n        <li>Upwork Job URL: https://www.upwork.com/jobs/~021973333993826358065</li>\n        <li>Upwork Job ID: 1973333993826358065</li>\n        <li>Last Price Increase: 2025-10-01</li>\n    </ul>\n</details>\n\n<details><summary>Issue Owner</summary>Current Issue Owner: @</details>\n\n<details><summary>Issue Owner</summary>Current Issue Owner: @twisterdotcom</details>",
    "closed_by": null,
    "reactions": {
      "url": "https://api.github.com/repos/Expensify/App/issues/71658/reactions",
      "total_count": 0,
      "+1": 0,
      "-1": 0,
      "laugh": 0,
      "hooray": 0,
      "confused": 0,
      "heart": 0,
      "rocket": 0,
      "eyes": 0
    },
    "timeline_url": "https://api.github.com/repos/Expensify/App/issues/71658/timeline",
    "performed_via_github_app": null,
    "state_reason": null
  }
]